yumrepos/__init__.py
yumrepos/app.py
yumrepos/fs_backend.py
yumrepos/backports/__init__.py
yumrepos/backports/functools_lru_cache.py
yumrepos-0.9.6.data/scripts/yumrepos
yumrepos-0.9.6.dist-info/DESCRIPTION.rst
yumrepos-0.9.6.dist-info/METADATA
yumrepos-0.9.6.dist-info/RECORD
yumrepos-0.9.6.dist-info/WHEEL
yumrepos-0.9.6.dist-info/metadata.json
yumrepos-0.9.6.dist-info/top_level.txt
yumrepos-0.9.6.dist-info/zip-safe
