Metadata-Version: 2.0
Name: yumrepos
Version: 0.9.6
Summary: yumrepos: simple yum repositories with minimal rest api
Home-page: https://github.com/arnehilmann/yumrepos
Author: Arne Hilmann
Author-email: arne.hilmann@gmail.com
License: UNKNOWN
Platform: UNKNOWN
Classifier: Development Status :: 3 - Alpha
Classifier: Programming Language :: Python
Requires-Dist: flask
Requires-Dist: werkzeug
